fastinterval.py
setup.py
fastinterval.egg-info/PKG-INFO
fastinterval.egg-info/SOURCES.txt
fastinterval.egg-info/dependency_links.txt
fastinterval.egg-info/requires.txt
fastinterval.egg-info/top_level.txt