Metadata-Version: 1.1
Name: fastinterval
Version: 0.1.1
Summary: Interval class and fasta access
Home-page: https://github.com/jamescasbon/fastinterval
Author: James Casbon
Author-email: casbon@gmail.com
License: UNKNOWN
Keywords: bioinformatics
Platform: UNKNOWN
Classifier: Development Status :: 4 - Beta
Classifier: Intended Audience :: Developers
Classifier: Intended Audience :: Science/Research
Classifier: Programming Language :: Python
Classifier: Topic :: Scientific/Engineering
